arduino_controller/__init__.py
arduino_controller/arduino_variable.py
arduino_controller/board_api.py
arduino_controller/datalogger.py
arduino_controller/modul_variable.py
arduino_controller/parseboards.py
arduino_controller/portcommand.py
arduino_controller/portrequest.py
arduino_controller/python_variable.py
arduino_controller/serialport.py
arduino_controller/basicboard/__init__.py
arduino_controller/basicboard/board.py
arduino_controller/serialreader/__init__.py
arduino_controller/serialreader/serialdetector.py
arduino_controller/serialreader/serialreader.py
ArduinoController-0.1.1568726333.dist-info/LICENSE.txt
ArduinoController-0.1.1568726333.dist-info/METADATA
ArduinoController-0.1.1568726333.dist-info/WHEEL
ArduinoController-0.1.1568726333.dist-info/top_level.txt
ArduinoController-0.1.1568726333.dist-info/RECORD
